odoo/addons/__init__.py
odoo/addons/mass_mailing_event_track/__init__.py
odoo/addons/mass_mailing_event_track/__manifest__.py
odoo/addons/mass_mailing_event_track/i18n/af.po
odoo/addons/mass_mailing_event_track/i18n/am.po
odoo/addons/mass_mailing_event_track/i18n/ar.po
odoo/addons/mass_mailing_event_track/i18n/bg.po
odoo/addons/mass_mailing_event_track/i18n/bs.po
odoo/addons/mass_mailing_event_track/i18n/ca.po
odoo/addons/mass_mailing_event_track/i18n/cs.po
odoo/addons/mass_mailing_event_track/i18n/da.po
odoo/addons/mass_mailing_event_track/i18n/de.po
odoo/addons/mass_mailing_event_track/i18n/el.po
odoo/addons/mass_mailing_event_track/i18n/en_GB.po
odoo/addons/mass_mailing_event_track/i18n/es.po
odoo/addons/mass_mailing_event_track/i18n/et.po
odoo/addons/mass_mailing_event_track/i18n/eu.po
odoo/addons/mass_mailing_event_track/i18n/fa.po
odoo/addons/mass_mailing_event_track/i18n/fi.po
odoo/addons/mass_mailing_event_track/i18n/fo.po
odoo/addons/mass_mailing_event_track/i18n/fr.po
odoo/addons/mass_mailing_event_track/i18n/fr_CA.po
odoo/addons/mass_mailing_event_track/i18n/gl.po
odoo/addons/mass_mailing_event_track/i18n/gu.po
odoo/addons/mass_mailing_event_track/i18n/he.po
odoo/addons/mass_mailing_event_track/i18n/hr.po
odoo/addons/mass_mailing_event_track/i18n/hu.po
odoo/addons/mass_mailing_event_track/i18n/id.po
odoo/addons/mass_mailing_event_track/i18n/is.po
odoo/addons/mass_mailing_event_track/i18n/it.po
odoo/addons/mass_mailing_event_track/i18n/ja.po
odoo/addons/mass_mailing_event_track/i18n/ka.po
odoo/addons/mass_mailing_event_track/i18n/kab.po
odoo/addons/mass_mailing_event_track/i18n/ko.po
odoo/addons/mass_mailing_event_track/i18n/lo.po
odoo/addons/mass_mailing_event_track/i18n/lt.po
odoo/addons/mass_mailing_event_track/i18n/lv.po
odoo/addons/mass_mailing_event_track/i18n/mk.po
odoo/addons/mass_mailing_event_track/i18n/mn.po
odoo/addons/mass_mailing_event_track/i18n/nb.po
odoo/addons/mass_mailing_event_track/i18n/ne.po
odooku_odoo_website_event-11.0.7.dist-info/LICENSE
odooku_odoo_website_event-11.0.7.dist-info/METADATA
odooku_odoo_website_event-11.0.7.dist-info/WHEEL
odooku_odoo_website_event-11.0.7.dist-info/top_level.txt
odooku_odoo_website_event-11.0.7.dist-info/RECORD
